Metadata-Version: 2.3
Name: just-semantic-search-cuda
Version: 2.5.0
Summary: Core interfaces for hybrid search implementations (CUDA version)
License: Apache-2.0
Keywords: python,llm,gpu,cuda,science,review,hybrid search,semantic search,gpu,cuda
Author: Alex Karmazin
Author-email: karmazinalex@gmail.com
Requires-Python: >=3.10,<3.15
Classifier: Development Status :: 3 - Alpha
Classifier: Intended Audience :: Developers
Classifier: License :: OSI Approved :: Apache Software License
Classifier: Operating System :: MacOS :: MacOS X
Classifier: Operating System :: Microsoft :: Windows
Classifier: Operating System :: POSIX :: Linux
Classifier: Operating System :: Unix
Classifier: Programming Language :: Python :: 3
Classifier: Programming Language :: Python :: 3.10
Classifier: Programming Language :: Python :: 3.11
Classifier: Programming Language :: Python :: 3.12
Classifier: Programming Language :: Python :: 3.13
Classifier: Programming Language :: Python :: 3.14
Provides-Extra: cuda
Requires-Dist: einops (>=0.8.0)
Requires-Dist: eliot (>=1.16.0)
Requires-Dist: eliot-tree (>=24.0.0)
Requires-Dist: pydantic (>=2.10.3)
Requires-Dist: scikit-learn (>=1.5.2)
Requires-Dist: sentence-transformers (>=3.3.1)
Requires-Dist: torch (==2.6.0+cu124)
Requires-Dist: transformers (>=4.49.0)
Requires-Dist: triton (>=2.3.0) ; extra == "cuda"
Requires-Dist: typer
